COPYRIGHT
LICENSE
MANIFEST.in
NOTICE
README.md
pyproject.toml
setup.cfg
setup.py
flux_burst_gke.egg-info/PKG-INFO
flux_burst_gke.egg-info/SOURCES.txt
flux_burst_gke.egg-info/dependency_links.txt
flux_burst_gke.egg-info/not-zip-safe
flux_burst_gke.egg-info/requires.txt
flux_burst_gke.egg-info/top_level.txt
fluxburst_gke/__init__.py
fluxburst_gke/plugin.py
fluxburst_gke/version.py