Metadata-Version: 2.1
Name: flux-burst-gke
Version: 0.0.11
Summary: A bursting plugin for Flux and GKE
Home-page: https://github.com/converged-computing/flux-burst-gke
Author: Vanessa Sochat
Author-email: vsoch@users.noreply.github.com
Maintainer: Vanessa Sochat
License: LICENSE
Keywords: flux,flux-framework,workflow,example,plugin
Platform: UNKNOWN
Classifier: Intended Audience :: Science/Research
Classifier: Intended Audience :: Developers
Classifier: License :: OSI Approved :: MIT License
Classifier: Programming Language :: Python
Classifier: Topic :: Software Development
Classifier: Topic :: Scientific/Engineering
Classifier: Operating System :: Unix
Classifier: Programming Language :: Python :: 3.8
Provides-Extra: all
License-File: LICENSE
License-File: NOTICE
